count_money/__init__.py
count_money/__main__.py
count_money/locale/en/LC_MESSAGES/count_money.mo
count_money/locale/en/LC_MESSAGES/count_money.po
count_money/locale/pt/LC_MESSAGES/count_money.mo
count_money/locale/pt/LC_MESSAGES/count_money.po
count_money-0.7.1.dist-info/LICENSE
count_money-0.7.1.dist-info/METADATA
count_money-0.7.1.dist-info/WHEEL
count_money-0.7.1.dist-info/entry_points.txt
count_money-0.7.1.dist-info/top_level.txt
count_money-0.7.1.dist-info/RECORD
