Metadata-Version: 2.1
Name: count-money
Version: 0.7.1
Summary: A tkinter based GUI application that helps you count money.
Home-page: https://no-title.victordomingos.com/projects/contar-dinheiro/
License: MIT
Project-URL: Documentation, https://github.com/victordomingos/ContarDinheiro.py/blob/master/README.md
Project-URL: Source, https://github.com/victordomingos/ContarDinheiro.py
Project-URL: Bug Reports, https://github.com/victordomingos/ContarDinheiro.py/issues
Keywords: money count sum coins bills gui accounting commerce
Platform: UNKNOWN
Classifier: Development Status :: 5 - Production/Stable 
Classifier: Environment :: MacOS X
Classifier: Intended Audience :: End Users/Desktop
Classifier: License :: OSI Approved :: MIT License
Classifier: Natural Language :: English
Classifier: Operating System :: OS Independent
Classifier: Operating System :: MacOS :: MacOS X
Classifier: Operating System :: Microsoft :: Windows
Classifier: Operating System :: POSIX :: Linux 
Classifier: Programming Language :: Python :: 3
Classifier: Programming Language :: Python :: 3.6
Classifier: Programming Language :: Python :: 3.7
Classifier: Programming Language :: Python :: 3.8
Classifier: Topic :: Utilities
Classifier: Topic :: Desktop Environment :: File Managers
Classifier: Topic :: System :: Filesystems
Requires-Python: >=3.6
